stmp/__init__.py
stmp/formatter_factory.py
stmp/main.py
stmp/sql/create_work_hours_view.sql
stmp/stmp.py
stmp-0.3.3.dist-info/LICENSE
stmp-0.3.3.dist-info/METADATA
stmp-0.3.3.dist-info/WHEEL
stmp-0.3.3.dist-info/entry_points.txt
stmp-0.3.3.dist-info/RECORD
