Metadata-Version: 2.1
Name: stmp
Version: 0.3.3
Summary: stmp - The tool to manage your working hours
Author: Hannes Ortmeier
Author-email: ortmeier.hannes@gmail.com
Requires-Python: >=3.11,<4.0
Classifier: Programming Language :: Python :: 3
Classifier: Programming Language :: Python :: 3.11
Classifier: Programming Language :: Python :: 3.12
Requires-Dist: pytest (>=7.4.3,<8.0.0)
Requires-Dist: sqlite-utils (>=3.35.2,<4.0.0)
Requires-Dist: tabulate (>=0.9.0,<0.10.0)
Requires-Dist: types-tabulate (>=0.9.0.3,<0.10.0.0)
